src/__init__.py
src/cli.py
src/models.py
src/print.py
src/utils.py
src/crawlers/__init__.py
src/crawlers/base.py
src/crawlers/linkedin.py
src/crawlers/reddit.py
src/crawlers/threads.py
src/crawlers/x.py
src/exporters/__init__.py
src/exporters/sheets_exporter.py
crawl_sns-0.1.0.dist-info/METADATA
crawl_sns-0.1.0.dist-info/WHEEL
crawl_sns-0.1.0.dist-info/entry_points.txt
crawl_sns-0.1.0.dist-info/licenses/LICENSE
crawl_sns-0.1.0.dist-info/RECORD
