Metadata-Version: 2.4
Name: crawl-sns
Version: 0.1.0
Summary: SNS 플랫폼(Threads, LinkedIn, X, Reddit)에서 게시글을 크롤링하는 도구
Project-URL: Homepage, https://github.com/yourusername/crawl-sns
Project-URL: Documentation, https://github.com/yourusername/crawl-sns#readme
Project-URL: Repository, https://github.com/yourusername/crawl-sns
Project-URL: Bug Tracker, https://github.com/yourusername/crawl-sns/issues
Author-email: Your Name <your.email@example.com>
Maintainer-email: Your Name <your.email@example.com>
License: MIT
License-File: LICENSE
Keywords: crawling,linkedin,reddit,scraping,sns,social-media,threads,twitter
Classifier: Development Status :: 4 - Beta
Classifier: Intended Audience :: Developers
Classifier: License :: OSI Approved :: MIT License
Classifier: Operating System :: OS Independent
Classifier: Programming Language :: Python :: 3
Classifier: Programming Language :: Python :: 3.12
Classifier: Topic :: Internet :: WWW/HTTP :: Indexing/Search
Classifier: Topic :: Software Development :: Libraries :: Python Modules
Classifier: Topic :: Text Processing :: Markup :: HTML
Requires-Python: >=3.12
Requires-Dist: playwright>=1.52.0
Requires-Dist: pydantic>=2.11.5
Requires-Dist: python-dotenv>=1.0.0
Requires-Dist: requests>=2.32.3
Requires-Dist: typer>=0.15.4
Provides-Extra: dev
Requires-Dist: black>=23.0.0; extra == 'dev'
Requires-Dist: flake8>=6.0.0; extra == 'dev'
Requires-Dist: isort>=5.12.0; extra == 'dev'
Requires-Dist: mypy>=1.5.0; extra == 'dev'
Requires-Dist: pylint>=2.17.0; extra == 'dev'
Requires-Dist: pytest>=7.0.0; extra == 'dev'
